{
  "cycle": 14,
  "cycle_hash": "d9c26343149cf9ecd0f66c7434dc2320920f7fca4702d45b66289023e20d3761",
  "timestamp": "2026-06-22T02:53:17.254955+00:00",
  "results": [
    {
      "endpoint": "HN-nacional-nacional",
      "success": false,
      "status": null,
      "hash": null,
      "latency_ms": 30999.8,
      "error": "timeout_after_30s"
    },
    {
      "endpoint": "HN-01-dept_01",
      "success": false,
      "status": null,
      "hash": null,
      "latency_ms": 30999.3,
      "error": "timeout_after_30s"
    },
    {
      "endpoint": "HN-02-dept_02",
      "success": false,
      "status": null,
      "hash": null,
      "latency_ms": 30999.7,
      "error": "timeout_after_30s"
    },
    {
      "endpoint": "HN-03-dept_03",
      "success": false,
      "status": null,
      "hash": null,
      "latency_ms": 30999.7,
      "error": "timeout_after_30s"
    },
    {
      "endpoint": "HN-04-dept_04",
      "success": false,
      "status": null,
      "hash": null,
      "latency_ms": 30999.4,
      "error": "timeout_after_30s"
    },
    {
      "endpoint": "HN-05-dept_05",
      "success": false,
      "status": null,
      "hash": null,
      "latency_ms": 30999.2,
      "error": "timeout_after_30s"
    },
    {
      "endpoint": "HN-06-dept_06",
      "success": false,
      "status": null,
      "hash": null,
      "latency_ms": 30999.4,
      "error": "timeout_after_30s"
    },
    {
      "endpoint": "HN-07-dept_07",
      "success": false,
      "status": null,
      "hash": null,
      "latency_ms": 30999.3,
      "error": "timeout_after_30s"
    },
    {
      "endpoint": "HN-08-dept_08",
      "success": false,
      "status": null,
      "hash": null,
      "latency_ms": 30999.3,
      "error": "timeout_after_30s"
    },
    {
      "endpoint": "HN-09-dept_09",
      "success": false,
      "status": null,
      "hash": null,
      "latency_ms": 30999.2,
      "error": "timeout_after_30s"
    },
    {
      "endpoint": "HN-10-dept_10",
      "success": false,
      "status": null,
      "hash": null,
      "latency_ms": 30999.2,
      "error": "timeout_after_30s"
    },
    {
      "endpoint": "HN-11-dept_11",
      "success": false,
      "status": null,
      "hash": null,
      "latency_ms": 30999.2,
      "error": "timeout_after_30s"
    },
    {
      "endpoint": "HN-12-dept_12",
      "success": false,
      "status": null,
      "hash": null,
      "latency_ms": 30999.0,
      "error": "timeout_after_30s"
    },
    {
      "endpoint": "HN-13-dept_13",
      "success": false,
      "status": null,
      "hash": null,
      "latency_ms": 30998.9,
      "error": "timeout_after_30s"
    },
    {
      "endpoint": "HN-14-dept_14",
      "success": false,
      "status": null,
      "hash": null,
      "latency_ms": 30999.0,
      "error": "timeout_after_30s"
    },
    {
      "endpoint": "HN-15-dept_15",
      "success": false,
      "status": null,
      "hash": null,
      "latency_ms": 30998.8,
      "error": "timeout_after_30s"
    },
    {
      "endpoint": "HN-16-dept_16",
      "success": false,
      "status": null,
      "hash": null,
      "latency_ms": 30998.8,
      "error": "timeout_after_30s"
    },
    {
      "endpoint": "HN-17-dept_17",
      "success": false,
      "status": null,
      "hash": null,
      "latency_ms": 30998.7,
      "error": "timeout_after_30s"
    },
    {
      "endpoint": "HN-18-dept_18",
      "success": false,
      "status": null,
      "hash": null,
      "latency_ms": 30998.7,
      "error": "timeout_after_30s"
    }
  ]
}